<?xml version="1.0" encoding="UTF-8"?>
<objects serializationModel="Studio.02.01.00">
	<object class="AudioFile" id="{2f6451f1-de7a-4575-bd27-319a5e7cbcf0}">
		<property name="assetPath">
			<value>laser_beam_61_start.wav</value>
		</property>
		<property name="frequencyInKHz">
			<value>48</value>
		</property>
		<property name="channelCount">
			<value>2</value>
		</property>
		<property name="length">
			<value>0.67910416666666662</value>
		</property>
		<relationship name="masterAssetFolder">
			<destination>{6888575e-aaf8-4e4d-bc05-472f70f5cbe6}</destination>
		</relationship>
	</object>
</objects>
